app/__init__.py
app/main.py
app/api/__init__.py
app/api/cgm.py
app/api/health.py
app/core/__init__.py
app/core/config.py
app/core/cors.py
app/models/__init__.py
app/models/cgm.py
app/services/__init__.py
app/services/cgm_service.py
loopy_api-1.0.0.dist-info/METADATA
loopy_api-1.0.0.dist-info/WHEEL
loopy_api-1.0.0.dist-info/RECORD
