Metadata-Version: 2.4
Name: loopy-api
Version: 1.0.0
Summary: FastAPI-based backend service for accessing CGM data from MongoDB. Built for DIY diabetes monitoring setups.
Requires-Python: >=3.12
Requires-Dist: fastapi>=0.104.0
Requires-Dist: loopy-basic>=0.1.0
Requires-Dist: pydantic-settings>=2.0.0
Requires-Dist: python-dotenv>=1.0.0
Requires-Dist: uvicorn[standard]>=0.24.0
Provides-Extra: dev
Requires-Dist: httpx>=0.25.0; extra == 'dev'
Requires-Dist: pytest-asyncio>=0.21.0; extra == 'dev'
Requires-Dist: pytest>=7.4.0; extra == 'dev'
Requires-Dist: ruff>=0.1.0; extra == 'dev'
